MANIFEST.in
README.rst
setup.py
collective/.DS_Store
collective/__init__.py
collective/__init__.pyc
collective.ptg.presentation.egg-info/PKG-INFO
collective.ptg.presentation.egg-info/SOURCES.txt
collective.ptg.presentation.egg-info/dependency_links.txt
collective.ptg.presentation.egg-info/entry_points.txt
collective.ptg.presentation.egg-info/namespace_packages.txt
collective.ptg.presentation.egg-info/not-zip-safe
collective.ptg.presentation.egg-info/requires.txt
collective.ptg.presentation.egg-info/top_level.txt
collective/ptg/.DS_Store
collective/ptg/__init__.py
collective/ptg/__init__.pyc
collective/ptg/presentation/.DS_Store
collective/ptg/presentation/__init__.py
collective/ptg/presentation/__init__.pyc
collective/ptg/presentation/configure.zcml
collective/ptg/presentation/presentation.pt
collective/ptg/presentation/resources/presentation-shadow.png
collective/ptg/presentation/resources/style.css
docs/HISTORY.txt
docs/INSTALL.txt
docs/LICENSE.GPL
docs/LICENSE.txt