Metadata-Version: 1.0
Name: collective.ptg.presentation
Version: 1.0.3
Summary: Adds a presentation gallery layout to collective.plonetruegallery
Home-page: http://svn.plone.org/svn/collective/
Author: Nathan Van Gheem
Author-email: vangheem@gmail.com
License: GPL
Keywords: plone plonetruegallery addon
Platform: UNKNOWN
Classifier: Framework :: Plone
Classifier: Programming Language :: Python
